odoo/addons/ssi_frequency/README.rst
odoo/addons/ssi_frequency/__init__.py
odoo/addons/ssi_frequency/__manifest__.py
odoo/addons/ssi_frequency/menu.xml
odoo/addons/ssi_frequency/demo/frequency_demo.xml
odoo/addons/ssi_frequency/models/__init__.py
odoo/addons/ssi_frequency/models/frequency.py
odoo/addons/ssi_frequency/models/frequency_set.py
odoo/addons/ssi_frequency/security/ir.model.access.csv
odoo/addons/ssi_frequency/static/description/icon.png
odoo/addons/ssi_frequency/views/frequency_set_views.xml
odoo/addons/ssi_frequency/views/frequency_views.xml
odoo14_addon_ssi_frequency-14.0.1.1.0.dist-info/METADATA
odoo14_addon_ssi_frequency-14.0.1.1.0.dist-info/WHEEL
odoo14_addon_ssi_frequency-14.0.1.1.0.dist-info/top_level.txt
odoo14_addon_ssi_frequency-14.0.1.1.0.dist-info/RECORD
